fakeshell/__init__.py
fakeshell/interpreter.py
fakeshell/shell.py
fakeshell/commands/__init__.py
fakeshell/commands/b64.py
fakeshell/commands/buildin.py
fakeshell/commands/cat.py
fakeshell/commands/chmod.py
fakeshell/commands/chown.py
fakeshell/commands/curl.py
fakeshell/commands/df.py
fakeshell/commands/grep.py
fakeshell/commands/ls.py
fakeshell/commands/md5sum.py
fakeshell/commands/mkdir.py
fakeshell/commands/network.py
fakeshell/commands/rm.py
fakeshell/commands/utils.py
fakeshell-1.0.1.dist-info/METADATA
fakeshell-1.0.1.dist-info/WHEEL
fakeshell-1.0.1.dist-info/top_level.txt
fakeshell-1.0.1.dist-info/RECORD
