Metadata-Version: 2.1
Name: fakeshell
Version: 1.0.1
Summary: A virtual shell implementation
Home-page: https://github.com/phishing-hunter/fakeshell
Author: tatsui
Author-email: 2360691+tatsu-i@users.noreply.github.com
License: UNKNOWN
Platform: UNKNOWN
Classifier: Programming Language :: Python :: 3
Classifier: License :: OSI Approved :: MIT License
Classifier: Operating System :: OS Independent
Requires-Python: >=3.6
Requires-Dist: psutil
Requires-Dist: humanfriendly
Requires-Dist: requests
Requires-Dist: pyfakefs
